RheaFlow/NetlinkProcessor.py
RheaFlow/RheaController.py
RheaFlow/RheaFastpath.py
RheaFlow/RheaFlowEvents.py
RheaFlow/RheaFlowProcessor.py
RheaFlow/RheaNLSocket.py
RheaFlow/RheaRouteReceiver.py
RheaFlow/RheaYAML.py
RheaFlow/__init__.py
RheaFlow/jsonHandler.py
RheaFlow/log.py
RheaFlow-0.0.24.data/data/bin/RheaManager
RheaFlow-0.0.24.data/data/etc/ryu/config.yaml
RheaFlow-0.0.24.data/data/etc/ryu/ryu.conf
RheaFlow-0.0.24.data/data/etc/systemd/system/NetlinkProcessor.service
RheaFlow-0.0.24.data/data/etc/systemd/system/RheaFlow.service
RheaFlow-0.0.24.dist-info/DESCRIPTION.rst
RheaFlow-0.0.24.dist-info/METADATA
RheaFlow-0.0.24.dist-info/RECORD
RheaFlow-0.0.24.dist-info/WHEEL
RheaFlow-0.0.24.dist-info/metadata.json
RheaFlow-0.0.24.dist-info/top_level.txt
