Metadata-Version: 2.0
Name: RheaFlow
Version: 0.0.24
Summary: Software defined network router
Home-page: https://github.com/wandsdn/RheaFlow
Author: Oladimeji Fayomi
Author-email: olafayomi@gmail.com
License:                                  Apache License
Requires-Dist: PyYAML
Requires-Dist: eventlet
Requires-Dist: netaddr
Requires-Dist: pyroute2
Requires-Dist: ryu
